<?xml version="1.0" encoding="UTF-8"?>
<files
  psalm-version="3.6.5@b1aae0d1a5a11908e0e5f9eb6795ab7bb3f43577"
  php-version="
    php:7.3.9;
    bcmath:7.3.9;
    calendar:7.3.9;
    Core:7.3.9;
    ctype:7.3.9;
    curl:7.3.8;
    date:7.3.9;
    dom:20031129;
    filter:7.3.9;
    gd:7.3.8;
    hash:7.3.9;
    iconv:7.3.9;
    intl:7.3.8;
    json:1.7.0;
    libxml:7.3.9;
    mbstring:7.3.8;
    mysqli:7.3.8;
    mysqlnd:mysqlnd 5.0.12-dev - 20150407 - $Id: 7cc7cc96e675f6d72e5cf0f267f48e167c2abb23 $;
    openssl:7.3.8;
    pcre:7.3.9;
    PDO:7.3.9;
    pdo_sqlite:7.3.8;
    Phar:7.3.9;
    readline:7.3.9;
    Reflection:7.3.9;
    session:7.3.9;
    SimpleXML:7.3.9;
    sodium:7.3.8;
    SPL:7.3.9;
    standard:7.3.9;
    tokenizer:7.3.9;
    wddx:7.3.9;
    xml:7.3.9;
    xmlreader:7.3.9;
    xmlwriter:7.3.9;
    zip:1.15.4;
    zlib:7.3.9
  "
>
  <file src="Tests/Fixtures/DateArgs.php">
    <MoreSpecificImplementedParamType occurrences="1">
      <code>$data</code>
    </MoreSpecificImplementedParamType>
  </file>
  <file src="Tests/Fixtures/IntIdArgs.php">
    <MoreSpecificImplementedParamType occurrences="1">
      <code>$args</code>
    </MoreSpecificImplementedParamType>
  </file>
  <file src="Tests/Fixtures/IntIdStringSlugArgs.php">
    <MoreSpecificImplementedParamType occurrences="1">
      <code>$args</code>
    </MoreSpecificImplementedParamType>
  </file>
  <file src="Tests/Fixtures/StringModeArgs.php">
    <MoreSpecificImplementedParamType occurrences="1">
      <code>$data</code>
    </MoreSpecificImplementedParamType>
  </file>
  <file src="Tests/ImplementationTest.php">
    <ArgumentTypeCoercion occurrences="2">
      <code>strrev($method)</code>
      <code>strrev($method)</code>
    </ArgumentTypeCoercion>
    <UnusedVariable occurrences="1">
      <code>$prevKey</code>
    </UnusedVariable>
  </file>
  <file src="src/Router/Dispatcher.php">
    <MoreSpecificImplementedParamType occurrences="1">
      <code>$httpMethod</code>
    </MoreSpecificImplementedParamType>
  </file>
  <file src="src/Router/RouteCollector.php">
    <MoreSpecificImplementedParamType occurrences="1">
      <code>$handler</code>
    </MoreSpecificImplementedParamType>
  </file>
</files>
